guidance/__init__.py
guidance/_ast.py
guidance/_grammar.py
guidance/_guidance.py
guidance/_guidance.pyi
guidance/_parser.py
guidance/_schema.py
guidance/_tools.py
guidance/_topics.py
guidance/_utils.py
guidance/chat.py
guidance/debug.py
guidance/py.typed
guidance/_bg/__init__.py
guidance/library/__init__.py
guidance/library/_audio.py
guidance/library/_block.py
guidance/library/_capture.py
guidance/library/_ebnf.py
guidance/library/_gen.py
guidance/library/_image.py
guidance/library/_json.py
guidance/library/_optional.py
guidance/library/_pydantic.py
guidance/library/_role.py
guidance/library/_sequences.py
guidance/library/_subgrammar.py
guidance/library/_substring.py
guidance/library/_video.py
guidance/metrics/__init__.py
guidance/metrics/_metrics.py
guidance/models/__init__.py
guidance/models/_azureai.py
guidance/models/_byte_tokenizer.py
guidance/models/_llama_cpp.py
guidance/models/_mock.py
guidance/models/_openai.py
guidance/models/_openai_base.py
guidance/models/_transformers.py
guidance/models/_base/__init__.py
guidance/models/_base/_interpreter.py
guidance/models/_base/_model.py
guidance/models/_base/_state.py
guidance/models/_engine/__init__.py
guidance/models/_engine/_engine.py
guidance/models/_engine/_interpreter.py
guidance/models/_engine/_state.py
guidance/models/_engine/_tokenizer.py
guidance/models/experimental/__init__.py
guidance/models/experimental/_litellm.py
guidance/models/experimental/_sglang.py
guidance/models/experimental/_vllm.py
guidance/registry/__init__.py
guidance/registry/_registry.py
guidance/resources/graphpaper-inline.html
guidance/resources/sample_audio.wav
guidance/resources/sample_image.png
guidance/resources/sample_video.mp4
guidance/trace/__init__.py
guidance/trace/_trace.py
guidance/visual/__init__.py
guidance/visual/_environment.py
guidance/visual/_exchange.py
guidance/visual/_jupyter.py
guidance/visual/_message.py
guidance/visual/_renderer.py
guidance/visual/_trace.py
guidance-0.3.0.dist-info/licenses/LICENSE.md
guidance-0.3.0.dist-info/METADATA
guidance-0.3.0.dist-info/WHEEL
guidance-0.3.0.dist-info/top_level.txt
guidance-0.3.0.dist-info/RECORD
