Metadata-Version: 2.4
Name: guidance
Version: 0.3.0
Summary: A guidance language for controlling large language models.
Home-page: https://github.com/guidance-ai/guidance
Author: Guidance Maintainers
Author-email: maintainers@guidance-ai.org
Requires-Python: >=3.9
License-File: LICENSE.md
Requires-Dist: jinja2
Requires-Dist: numpy
Requires-Dist: pydantic
Requires-Dist: requests
Requires-Dist: psutil
Requires-Dist: guidance-stitch==0.1.5
Requires-Dist: llguidance==1.1.0
Provides-Extra: all
Requires-Dist: azure-ai-inference; extra == "all"
Requires-Dist: openai>=1.0; extra == "all"
Provides-Extra: unittest
Requires-Dist: anytree; extra == "unittest"
Requires-Dist: jsonschema; extra == "unittest"
Requires-Dist: pytest; extra == "unittest"
Requires-Dist: pytest-cov; extra == "unittest"
Requires-Dist: pytest-asyncio; extra == "unittest"
Requires-Dist: tokenizers; extra == "unittest"
Provides-Extra: llamacpp
Requires-Dist: llama-cpp-python==0.3.14; extra == "llamacpp"
Provides-Extra: transformers
Requires-Dist: transformers==4.53.3; extra == "transformers"
Provides-Extra: test
Requires-Dist: types-regex; extra == "test"
Requires-Dist: types-requests; extra == "test"
Requires-Dist: types-jsonschema; extra == "test"
Requires-Dist: diskcache; extra == "test"
Requires-Dist: requests; extra == "test"
Requires-Dist: azure-identity; extra == "test"
Requires-Dist: bitsandbytes; extra == "test"
Requires-Dist: jupyter; extra == "test"
Requires-Dist: papermill; extra == "test"
Requires-Dist: pillow; extra == "test"
Requires-Dist: protobuf; extra == "test"
Requires-Dist: sentencepiece; extra == "test"
Requires-Dist: torch; extra == "test"
Requires-Dist: transformers; extra == "test"
Requires-Dist: tiktoken>=0.3; extra == "test"
Requires-Dist: mypy==1.9.0; extra == "test"
Requires-Dist: anytree; extra == "test"
Requires-Dist: jsonschema; extra == "test"
Requires-Dist: pytest; extra == "test"
Requires-Dist: pytest-cov; extra == "test"
Requires-Dist: pytest-asyncio; extra == "test"
Requires-Dist: tokenizers; extra == "test"
Provides-Extra: docs
Requires-Dist: ipython; extra == "docs"
Requires-Dist: nbsphinx; extra == "docs"
Requires-Dist: numpydoc; extra == "docs"
Requires-Dist: sphinx_rtd_theme; extra == "docs"
Requires-Dist: sphinx; extra == "docs"
Requires-Dist: ipykernel; extra == "docs"
Requires-Dist: huggingface_hub; extra == "docs"
Requires-Dist: llama-cpp-python; extra == "docs"
Provides-Extra: dev
Requires-Dist: ruff==0.11.11; extra == "dev"
Requires-Dist: mypy; extra == "dev"
Provides-Extra: azureai
Requires-Dist: openai>=1.0; extra == "azureai"
Requires-Dist: azure-ai-inference; extra == "azureai"
Provides-Extra: openai
Requires-Dist: openai>=1.0; extra == "openai"
Dynamic: author
Dynamic: author-email
Dynamic: description
Dynamic: home-page
Dynamic: license-file
Dynamic: provides-extra
Dynamic: requires-dist
Dynamic: requires-python
Dynamic: summary
